fastappkit/__init__.py
fastappkit/cli/__init__.py
fastappkit/cli/app.py
fastappkit/cli/core.py
fastappkit/cli/main.py
fastappkit/cli/migrate.py
fastappkit/cli/output.py
fastappkit/cli/templates/.gitkeep
fastappkit/cli/templates/app/external/.gitignore.j2
fastappkit/cli/templates/app/external/README.md.j2
fastappkit/cli/templates/app/external/__init__.py.j2
fastappkit/cli/templates/app/external/alembic.ini.j2
fastappkit/cli/templates/app/external/config.py.j2
fastappkit/cli/templates/app/external/env.example.j2
fastappkit/cli/templates/app/external/fastappkit.toml.j2
fastappkit/cli/templates/app/external/main.py.j2
fastappkit/cli/templates/app/external/migrations/env.py.j2
fastappkit/cli/templates/app/external/migrations/script.py.mako.j2
fastappkit/cli/templates/app/external/models.py.j2
fastappkit/cli/templates/app/external/pyproject.toml.j2
fastappkit/cli/templates/app/external/router.py.j2
fastappkit/cli/templates/app/internal/__init__.py.j2
fastappkit/cli/templates/app/internal/migrations/README.md.j2
fastappkit/cli/templates/app/internal/migrations/env.py.j2
fastappkit/cli/templates/app/internal/migrations/script.py.mako.j2
fastappkit/cli/templates/app/internal/models.py.j2
fastappkit/cli/templates/app/internal/router.py.j2
fastappkit/cli/templates/project/.gitignore.j2
fastappkit/cli/templates/project/README.md.j2
fastappkit/cli/templates/project/core/__init__.py.j2
fastappkit/cli/templates/project/core/app.py.j2
fastappkit/cli/templates/project/core/config.py.j2
fastappkit/cli/templates/project/core/db/__init__.py.j2
fastappkit/cli/templates/project/core/db/migrations/env.py.j2
fastappkit/cli/templates/project/core/db/migrations/script.py.mako.j2
fastappkit/cli/templates/project/core/models.py.j2
fastappkit/cli/templates/project/env.example.j2
fastappkit/cli/templates/project/fastappkit.toml.j2
fastappkit/cli/templates/project/main.py.j2
fastappkit/cli/templates/project/pyproject.toml.j2
fastappkit/cli/templates.py
fastappkit/conf/__init__.py
fastappkit-0.2.2.dist-info/METADATA
fastappkit-0.2.2.dist-info/WHEEL
fastappkit-0.2.2.dist-info/entry_points.txt
fastappkit-0.2.2.dist-info/licenses/LICENSE
fastappkit-0.2.2.dist-info/RECORD
