Metadata-Version: 2.4
Name: fastappkit
Version: 0.2.2
Summary: A toolkit for building FastAPI projects with apps - internal and external pluggable apps
License: MIT
License-File: LICENSE
Keywords: fastapi,apps,plugins,migrations,framework,django-like,modular,alembic
Author: VanyLabs
Author-email: desaiparth971@gmail.com
Requires-Python: >=3.11,<4.0
Classifier: Development Status :: 3 - Alpha
Classifier: Framework :: FastAPI
Classifier: Intended Audience :: Developers
Classifier: License :: OSI Approved :: MIT License
Classifier: Programming Language :: Python :: 3
Classifier: Programming Language :: Python :: 3.11
Classifier: Programming Language :: Python :: 3.12
Classifier: Programming Language :: Python :: 3.13
Classifier: Programming Language :: Python :: 3.14
Classifier: Topic :: Internet :: WWW/HTTP :: HTTP Servers
Classifier: Topic :: Software Development :: Libraries :: Python Modules
Classifier: Typing :: Typed
Requires-Dist: alembic (>=1.17.2,<1.18)
Requires-Dist: fastapi (>=0.120.0,<0.130)
Requires-Dist: jinja2 (>=3.1.6,<4.0)
Requires-Dist: pydantic-settings (>=2.10.0,<3.0)
Requires-Dist: rich (>=14.0.0,<15.0)
Requires-Dist: sqlalchemy (>=2.0,<3.0)
Requires-Dist: tomlkit (>=0.13.3,<0.14)
Requires-Dist: typer (>=0.20.0,<0.21)
Requires-Dist: uvicorn[standard] (>=0.38.0,<0.39)
Project-URL: Documentation, https://fastappkit.readthedocs.io
Project-URL: Homepage, https://github.com/vanylabs/fastappkit
Project-URL: Repository, https://github.com/vanylabs/fastappkit
